Workbook

Sheet README
A1: R.R. Garden Booking & Rate Tracker
A3: Sheets in this workbook:
A4: 1. Guest Register — every individual booking from the handwritten register (name, ID details, dates, room). Currently loaded: Page 1 of 60 (12 bookings) as a working sample.
A5: 2. Hisaab Bookings — raw room-rate data (date + amount per room booked) from the June-July 2026 diary pages. This is the only rate data found in the scan.
A6: 3. Monthly Rate Trend — auto-calculated average/min/max rate and revenue per month, with a chart. Add more months to 'Hisaab Bookings' and it updates automatically.
A7: 4. Settlement Notes — the income-split scribbles under the June totals (Uncle/Ansh/Malwa/Online/Baki). Meaning is a best guess — please confirm.
A8: 5. Expenses — blank tracker for ongoing costs (repairs, supplies, staff etc.)
A10: IMPORTANT:
A11: - Yellow highlighted cells = handwriting was unclear in the scan. Please verify against the physical register before relying on them.
A12: - The register has ~700+ total bookings across 60 pages — only page 1 is digitized so far. Send more pages (clear, well-lit photos work best) and I'll keep adding rows.
A13: - Room rates only exist in the June/July diary — older register pages (Aug 2024 onward) record guest ID details but no price, so historical rate trend before May 2026 isn't available unless you have another rate record.

Sheet Guest Register
A1: R.R. Garden — Guest Register
A2: Digitized from handwritten register. Loaded: Page 1 (rows above) + pages 2-25 appended below (290 more bookings). Yellow cells = unclear handwriting (VERIFY) - check against physical register.
A4: PageNo | B4: SNo | C4: GuestName | D4: Age | E4: Relationship | F4: Nationality | G4: NumPersons | H4: Address | I4: Phone | J4: ComingFrom | K4: NextDestination | L4: Purpose | M4: ArrivalDateTime | N4: DepartureDateTime | O4: RoomNo
A5: 1 | B5: 1 | C5: Naitik Sharma / Aarti Rajput | D5: 21 / 11 | E5: Friend | F5: India | G5: 2 | H5: 175/2 Sanjay G.N. Naubasti, Gulab Nagar Naubasti, Kanpur | I5: 8229360908 | J5: Kalyanpur | K5: Kalyanpur | L5: Visit | M5: 8/11/24 7:20pm | N5: 8/11/24 8:10pm | O5: 201
A6: 1 | B6: 2 | C6: Abhay / Anjali | D6: 20 / 22 | E6: Friend | F6: India | G6: 2 | H6: 429 Bakfuri Purwa, 999 Devidhi Nagar | I6: 9696972862 | J6: Kanpur | K6: Kanpur | L6: Visit | M6: 9/11/24 12:35pm | N6: 9/11/24 4:20pm | O6: 201
A7: 1 | B7: 3 | C7: Sonu / Stuti | D7: 21 / 20 | E7: Friend | F7: India | G7: 2 | H7: Chak Bijay Harishpur, Lal Bagla Kanpur | I7: 6392813154 | J7: Kanpur | K7: Kanpur | L7: Visit | M7: 9/11/24 3:15pm | N7: 9/11/24 4:19pm | O7: 202
A8: 1 | B8: 4 | C8: Annu Tiwari / Ayush Sharma | D8: VERIFY / 19 | E8: Friend | F8: India | G8: 2 | H8: Naubasti Kanpur | I8: 6391189513 | J8: Kanpur | K8: Kanpur | L8: Visit | M8: 9/11/24 5:28pm | N8: 9/11/24 7:30pm | O8: 202
A9: 1 | B9: 5 | C9: Akshat / Roshani | D9: 20 / 22 | E9: Friend | F9: India | G9: 2 | H9: Dabauli Udyan Kanpur | I9: 7892064742 | J9: Kanpur | K9: Kanpur | L9: Visit | M9: 12/11/24 1:36pm | N9: 12/11/24 4:30pm | O9: 201
A10: 1 | B10: 6 | C10: Ram Prakash / Puja Singh | D10: VERIFY / 28 | E10: Friend | F10: India | G10: 2 | H10: Dada Nagar Kanpur | I10: 9909182961 | J10: Kanpur | K10: Kanpur | L10: Visit | M10: 12/11/24 2:20pm | N10: 12/11/24 5:30pm | O10: 202
A11: 1 | B11: 7 | C11: Ankit Rajput / Puja Soni | D11: 19 / 20 | E11: Friend | F11: India | G11: 2 | H11: Kathagar / Naubasti Kanpur | I11: 63866809 | J11: Kanpur | K11: Kanpur | L11: Visit | M11: 15/11/24 10:48am | N11: 15/11/24 1:28pm | O11: 202
A12: 1 | B12: 8 | C12: Vishal Rajput / Preeti | D12: 18 / 21 | E12: Friend | F12: India | G12: 2 | H12: Maal Kanpur / Kathagar Kanpur | I12: 6306078691 | J12: Kanpur | K12: Kanpur | L12: Visit | M12: 15/11/24 1:05pm | N12: 15/11/24 6:10pm | O12: 203
A13: 1 | B13: 9 | C13: Shweta / Ankit Singh | D13: 24 / 30 | E13: Friend | F13: India | G13: 2 | H13: Gram Berri Kalyanpur / Parsapur Purv Kanpur | I13: 8542845591 | J13: Kanpur | K13: Kanpur | L13: Visit | M13: 16/11/24 12:41pm | N13: 16/11/24 3:48pm | O13: 201
A14: 1 | B14: 10 | C14: Zeeshan / Umran Khatoon | D14: 43 / 38 | E14: Friend | F14: India | G14: 2 | H14: Kakadeo / Naubasti Kanpur | I14: 9696911758 | J14: Kanpur | K14: Kanpur | L14: Visit | M14: 19/11/24 7:15am | N14: 19/11/24 11:30am | O14: 201
A15: 1 | B15: 11 | C15: Ankit Kumar / Jyoti Yadav | D15: 28 / 26 | E15: Friend | F15: India | G15: 2 | H15: Panki / Kanpur Dehat | I15: VERIFY | J15: Kanpur | K15: Kanpur | L15: Visit | M15: 19/11/24 11:40am | N15: 19/11/24 2:30pm | O15: 202
A16: 1 | B16: 12 | C16: Abhay / Anjali | D16: 18 / 18 | E16: Friend | F16: India | G16: 2 | H16: 429 Bakchi Purwa / 999 Devidhi Nagar | I16: 9696972862 | J16: Kanpur | K16: Kanpur | L16: Visit | M16: 20/11/24 10:20am | N16: 20/11/24 4:40pm | O16: 201
A17: 2 | B17: 13 | C17: Utkarsh / Pooja | D17: 21 / 19 | E17: Friend | F17: Indian | G17: 2 | H17: Barra-8 / Barra-2 | I17: 6382679848 | J17: Kanpur | K17: Kanpur | L17: Visit | M17: 20/11/24 4:40pm | N17: 20/11/24 5:20pm | O17: 202
A18: 2 | B18: 14 | C18: Anurag / Jyoti | D18: 20 / 20 | E18: Friend | F18: Indian | G18: 2 | H18: C-684 World Bank Barra Kanpur / Barra-2 Kanpur | I18: 9335681286 | J18: Kanpur | K18: Kanpur | L18: Visit | M18: 20/11/24 4:52pm | N18: 20/11/24 8:10pm | O18: 203
A19: 2 | B19: 15 | C19: Balwan Singh / Ankita | D19: 27 / 23 | E19: Friend | F19: Indian | G19: 2 | H19: Yojana Nagar / Bhognipur Kanpur Dehat | I19: 8468061150 | J19: Kanpur | K19: Kanpur | L19: Visit | M19: 21/11/24 1:15pm | N19: 21/11/24 4:20pm | O19: 201
A20: 2 | B20: 16 | C20: Abhay Kumar / Sneha Pal | D20: 23 / 20 | E20: Friend | F20: Indian | G20: 2 | H20: Lal Bangla Kanpur | I20: VERIFY 6386717471 | J20: Kanpur | K20: Kanpur | L20: Visit | M20: 22/11/24 9:50am | N20: 22/11/24 1:15pm | O20: 201
A21: 2 | B21: 17 | C21: Sandeep Kumar / Saloni Rathore | D21: 20 / 21 | E21: Friend | F21: Indian | G21: 2 | H21: KP University, Kanpur Nagar | I21: 8957011856 | J21: Kanpur | K21: Kanpur | L21: Visit | M21: 23/11/24 12:42pm | N21: 23/11/24 4:43pm | O21: 202
A22: 2 | B22: 18 | C22: Divyansh Shukla / Ananya Mishra | D22: 20 / 21 | E22: Friend | F22: Indian | G22: 2 | H22: Naubasta / Naubasta Kanpur | I22: 9554346863 | J22: Kanpur | K22: Kanpur | L22: Visit | M22: 25/11/24 10:20am | N22: 25/11/24 2:10pm | O22: 202
A23: 2 | B23: 19 | C23: Alok Tiwari / Aarti Savita | D23: 20 / 34 | E23: Friend | F23: Indian | G23: 2 | H23: CTG Dabauli Kanpur / Ratanlal Nagar Kanpur | I23: 6392813154 | J23: Kanpur | K23: Kanpur | L23: Visit | M23: 25/11/24 12:28pm | N23: 25/11/24 7:17pm | O23: 201
A24: 2 | B24: 20 | C24: Pratham / Saloni | D24: 25 / 24 | E24: Friend | F24: Indian | G24: 2 | H24: T.P. Nagar Kanpur / T.P. Nagar | I24: 7905019018 | J24: Kanpur | K24: Kanpur | L24: Visit | M24: 25/11/24 12:20pm | N24: 25/11/24 2:30pm | O24: 204
A25: 2 | B25: 21 | C25: Abhay / Anjali | D25: 20 / 22 | E25: Friend | F25: Indian | G25: 2 | H25: 479 Bhaktauri Purwa / 499 Dwivedi Nagar | I25: 9696972862 | J25: Kanpur | K25: Kanpur | L25: Visit | M25: 28/11/24 1:04pm | N25: 28/11/24 5:50pm | O25: 203
A26: 2 | B26: 22 | C26: Abhay / Anjali | D26: 20 / 22 | E26: Friend | F26: Indian | G26: 2 | H26: 428 Bhaktauri Purwa / 421 Dwivedi Nagar | I26: 9696972862 | J26: Kanpur | K26: Kanpur | L26: Visit | M26: 28/11/24 4:50pm | N26: 29/11/24 9:50pm | O26: 202
A27: 2 | B27: 23 | C27: Alok Tiwari / Aarti Savita | D27: 20 / 21 | E27: Friend | F27: Indian | G27: 2 | H27: CTG Dabauli Kanpur / Ratanlal Nagar Kanpur | I27: 6392813154 | J27: Kanpur | K27: Kanpur | L27: Visit | M27: 28/11/24 7:10pm | N27: 29/11/24 9:55pm | O27: 203
A28: 2 | B28: 24 | C28: Sandeep Kumar / Saloni Rathore | D28: 20 / 21 | E28: Friend | F28: Indian | G28: 2 | H28: KP University Kanpur | I28: 8957011056 | J28: Kanpur | K28: Kanpur | L28: Visit | M28: 29/11/24 3:37pm | N28: 29/11/24 6:38pm | O28: 202
A29: 3 | B29: 25 | C29: Abhay / Anjali | D29: 20 / 21 | E29: Friend | F29: Indian | G29: 2 | H29: - | J29: Kanpur | K29: Kanpur | L29: Visit | M29: 29/11/24 6:10pm | N29: 29/11/24 10:01pm | O29: 202
A30: 3 | B30: 26 | C30: Zeeshan / Umran Khatoon | D30: 43 / 38 | E30: Friend | F30: Indian | G30: 2 | H30: Kakadeo Kanpur | J30: Kanpur | K30: Kanpur | L30: Visit | M30: 30/11/24 6:15am | N30: 30/11/24 9:58am | O30: 203
A31: 3 | B31: 27 | C31: Aman Verma / Sweta Pathak | D31: 19 / 19 | E31: Friend | F31: Indian (Passport BR02303975) | G31: 2 | H31: Rail Bazar Kanpur / Naubasta Kanpur | I31: 9451930495 | J31: Kanpur | K31: Kanpur | L31: Visit | M31: 30/11/24 8:17am | N31: 30/11/24 10:37am | O31: 202
A32: 3 | B32: 28 | C32: Krish Ranjan / Aditi Goda | D32: 26 / 20 | E32: Friend | F32: Indian | G32: 2 | H32: Burari New Delhi / Jhansi Mandi Road | I32: 9560087592 | J32: Delhi | K32: Delhi | L32: PSIT Counselling | M32: 30/11/24 8:55am | N32: 30/11/24 4:02pm | O32: 201
A33: 3 | B33: 29 | C33: Dolly / Harsh Siyen | D33: 20 / 20 | E33: Friend | F33: Indian | G33: 2 | H33: Sarigawan Kanpur | I33: 6386994805 | J33: Kanpur | K33: Kanpur | L33: Visit | M33: 30/11/24 9:38am | N33: 30/11/24 3:38pm | O33: 204
A34: 3 | B34: 30 | C34: Abhishek / Nainshi | D34: 21 / 21 | E34: Friend | F34: Indian | G34: 2 | H34: Kaindha Kanpur Nagar | I34: 9555655493 | J34: Kanpur | K34: Kanpur | L34: Visit | M34: 30/11/24 11:48am | N34: 30/11/24 5:40pm | O34: 205
A35: 3 | B35: 31 | C35: Prashant Gautam / Deeksha Katiyar | D35: 19 / 18 | E35: Friend | F35: Indian | G35: 2 | H35: Sikandra Kanpur Dehat | I35: 6388895511 | J35: Kanpur | K35: Kanpur | L35: Visit | M35: 1/12/24 1:20pm | N35: 1/12/24 4:40pm | O35: 202
A36: 3 | B36: 32 | C36: Ankit Rajput / Puja Soni | D36: 19 / 20 | E36: Friend | F36: Indian | G36: 2 | H36: Kathagar Kanpur / Naubasta Kanpur | I36: 6386680960 | J36: Kanpur | K36: Kanpur | L36: Visit | M36: 1/12/24 1:34pm | N36: 1/12/24 4:25pm | O36: 203
A37: 3 | B37: 33 | C37: Deepu Sonkar / Payal Yadav | D37: 21 / 22 | E37: Friend | F37: Indian | G37: 2 | H37: Mardanpur Kanpur Nagar | I37: 6394010145 | J37: Kanpur | K37: Kanpur | L37: Visit | M37: 1/12/24 2:15pm | N37: 1/12/24 5:02pm | O37: 204
A38: 3 | B38: 34 | C38: Ritik Kumar / Pooja | D38: 22 / 22 | E38: Friend | F38: Indian | G38: 2 | H38: Udhyog Nagar Kanpur / Barra Kanpur | I38: 9336648998 | J38: Kanpur | K38: Kanpur | L38: Visit | M38: 1/12/24 4:08pm | N38: 1/12/24 4:30pm | O38: 201
A39: 3 | B39: 35 | C39: Pushpendra Pal | D39: 28 | E39: Friend | F39: Indian | G39: 1 | H39: Barra Kanpur | J39: Kanpur | K39: Kanpur | L39: Visit | M39: 2/12/24 1:15pm | N39: 2/12/24 5:15pm | O39: 202
A40: 3 | B40: 36 | C40: Amit Pal / Sakshi Tiwari | D40: 25 / 23 | E40: Friend | F40: Indian | G40: 2 | H40: Jarauli P-2 Kanpur / World Bank Barra-2 | I40: 7380621774 | J40: Kanpur | K40: Kanpur | L40: Visit | M40: 4/12/24 12:08pm | N40: 4/12/24 7:10pm | O40: 202
A41: 4 | B41: 37 | C41: Santosh Diwakar / Jyoti | D41: 24 / 24 | E41: Friend | F41: Indian | G41: 2 | H41: Juhi Colony Kanpur | I41: 8858377720 | J41: Kanpur | K41: Kanpur | L41: Visit | M41: 4/12/24 12:50pm | N41: 4/12/24 3:10pm | O41: 203
A42: 4 | B42: 38 | C42: Shubham Bagde / Niraj Kumar / Abhishek Kumar | D42: 26 / 25 / 27 | E42: Friend | F42: Indian | G42: 3 | H42: Balaghat (M.P.) / Jagatpur Bihar / Nalanda Bihar | I42: 9749471640 | J42: Balaghat / Nalanda | K42: Balaghat / Nalanda | L42: Training | M42: 4/12/24 1:20pm | O42: 204
A43: 4 | B43: 39 | C43: Nikhil | D43: 22 | E43: Friend | F43: Indian | G43: 1 | H43: Naubasta Kanpur Nagar | I43: 7309064199 | J43: Kanpur | K43: Kanpur | L43: Visit | M43: 5/12/24 11:40 | O43: 202
A44: 4 | B44: 40 | C44: Ankush / Anju | D44: 27 / 24 | E44: Friend | F44: Indian | G44: 2 | H44: - | I44: 8858787467 | J44: Kanpur | K44: Kanpur | L44: Visit | M44: 8/12/24 11:30am | N44: 8/12/24 4:30pm | O44: 201
A45: 4 | B45: 41 | C45: Naitik Sharma / Aarti | E45: Friend | F45: Indian | G45: 2 | H45: 175/2 Sanjay Gandhi Nagar Naubasta Kanpur | I45: VERIFY 888721913 (9 digits as written) | J45: Kanpur | K45: Kanpur | L45: Visit | M45: 8/12/24 7:15pm | N45: 8/12/24 | O45: 202
A46: 4 | B46: 42 | C46: Abhishek / Bhavya Bajpai | D46: 19 / 18 | E46: Friend | F46: Indian | G46: 2 | H46: 125 Sanjay Gandhi Nagar Naubasta Kanpur | I46: 7389719431 | J46: Kanpur | K46: Kanpur | L46: Visit | M46: 9/12/24 11:30am | N46: 9/12/24 2:23pm | O46: 201
A47: 4 | B47: 43 | C47: Aditya / Prinku Kumari | D47: 19 / 19 | E47: Friend | F47: Indian (ID 617989404989) | G47: 2 | H47: K-49 World Bank Barra Kanpur | I47: 8112878912 | J47: Kanpur | K47: Kanpur | L47: Visit | M47: 9/12/24 12:10pm | N47: 9/12/24 1:10pm | O47: 202
A48: 4 | B48: 44 | C48: Ranjeet Singh / Simran Singh | D48: 50 / 22 | E48: Friend | F48: Indian (Aadhaar 233691668999) | G48: 2 | H48: - | I48: 9936019961 | J48: Kanpur | K48: Kanpur | L48: Visit | M48: 9/12/24 7:59pm
A49: 4 | B49: 45 | C49: Abhay / Anjali | D49: 20 / 20 | E49: Friend | F49: India | G49: 2 | H49: 479 Baktauri Purwa | I49: 9696972862 | J49: Kanpur | K49: Kanpur | L49: Visit | M49: 11/12/24 4:30pm | N49: 11/12/24
A50: 4 | B50: 46 | C50: Sandeep Kumar / Saloni | D50: 20 / 21 | E50: Friend | F50: India (IDs 858598889385, 438672829438) | G50: 2 | H50: 358 K.P. (Hindi, unclear) | I50: 8957011856 | J50: Kanpur | K50: Kanpur | L50: Visit | M50: 11/12/24 4:38pm | N50: 11/12/24 6:28pm
A51: 4 | B51: 47 | C51: Siddhant / Khushi | D51: 18 / 18 | E51: Friend | F51: Indian (IDs S0961451922 / 08322586304) | G51: 2 | H51: Govind Nagar | I51: VERIFY 0997816972 (0040033089 struck out) | J51: Kanpur | K51: Kanpur | L51: Visit | M51: 11/12/24 11:45 | N51: 11/12/24 4:00pm | O51: 202
A52: 4 | B52: 48 | C52: Pratham Gupta / Salomi | D52: 24 / 21 | E52: Friend | F52: Indian | G52: 2 | H52: - | I52: 9838510455 | J52: Kanpur | K52: Kanpur | L52: Visit | M52: 13/12/24 | N52: 13/12/24
A53: 5 | B53: 49 | C53: Reshmi / Akshat | D53: 22 / 24 | E53: Friend | F53: Indian (IDs 934511336989, 9505...) | G53: 2 | H53: 33E/9, 2nd Udyog Nagar Kanpur (Hindi) | I53: 8445247938 | J53: Kanpur | K53: Kanpur | L53: Visit | M53: 13/12/24 4:20pm | N53: 13/12/24 6:35pm | O53: 201
A54: 5 | B54: 50 | C54: Alok / Savita | D54: 20 / 24 | E54: Friend | F54: Indian (IDs 869854011974, 245808476904) | G54: 2 | H54: Devli West Kanpur / Ratan Lal Nagar (Hindi) | I54: 7080956577 | J54: Kanpur | K54: Kanpur | L54: Visit | M54: 14/12/24 12:15pm | N54: 14/12/24 4:59pm | O54: 202
A55: 5 | B55: 51 | C55: (Hindi name) / Arti | D55: 24 / 24 | E55: Friend | F55: Indian (IDs 442301316113, 476830470187) | G55: 2 | H55: 612 (Hindi) | I55: 8858377320 | J55: Kanpur | K55: Kanpur | L55: Visit | M55: 15/12/24 12:32pm | N55: 15/12/24 2:40pm | O55: 201
A56: 5 | B56: 52 | C56: Aman / Shaivee | D56: 22 / 21 | E56: Friend | F56: Indian (IDs 663341976909, 897275107569) | G56: 2 | H56: 67 Bhauri Road Ramaipur | I56: 9129124101 | J56: Kanpur | K56: Kanpur | L56: Visit | M56: 16/12/24 9:04am | N56: 16/12/24 11:00am | O56: 202
A57: 5 | B57: 53 | C57: Abhay / Anjali | D57: 20 / 20 | E57: Friend | F57: Indian (IDs 309719208445, 501274126550) | G57: 2 | H57: Dwivedi Nagar Naubasta Kanpur | I57: 9696972862 | J57: Kanpur | K57: Kanpur | L57: Visit | M57: 17/12/24 3:15pm | N57: 17/12/24 10:00pm | O57: 201
A58: 5 | B58: 54 | C58: Sandeep Kumar / Saloni Rathore | D58: 20 / 21 | E58: Friend | F58: Indian (IDs 858598889385, 438672829438) | G58: 2 | H58: K.P University Kanpur | I58: 8957011856 | J58: Kanpur | K58: Kanpur | L58: Visit | M58: 17/12/24 4:08pm | N58: 17/12/24 6:30pm | O58: 202
A59: 5 | B59: 55 | C59: Naitik Sharma / Aarti Rajput | D59: 23 / 20 | E59: Friend | F59: Indian (IDs 426777347831, 450367271649) | G59: 2 | H59: 175/2 Sanjay Gandhi Nagar | I59: 8429360908 | J59: Kanpur | K59: Kanpur | L59: Visit | M59: 18/12/24 11:34am | N59: 18/12/24 2:15pm | O59: 201
A60: 5 | B60: 56 | C60: Ankit Singh / Km Shweta | D60: 30 / 24 | E60: Friend | F60: Indian (IDs 717704450267, 555780750784) | G60: 2 | H60: Dakshin Para Fatehpur Kanpur | I60: 8542845391 | J60: Kanpur | K60: Kanpur | L60: Visit | M60: 18/12/24 1:57pm | N60: 18/12/24 5:30pm | O60: 202
A61: 5 | B61: 57 | C61: Amit Kumar Pal / Shakshi Tiwari | D61: 25 / 23 | E61: Friend | F61: Indian (IDs 881719681296, 426183674046) | G61: 2 | H61: Jarauli Phase-2 / Bihari Purwa Barra Kanpur | I61: 7380621774 | J61: Kanpur | K61: Kanpur | L61: Visit | M61: 19/12/24 12:33pm | N61: 19/12/24 7:30pm | O61: 201
A62: 5 | B62: 58 | C62: Bhanu Tiwari / Raksha Kesarwani | D62: 26 / 25 | E62: Friend | F62: Indian (IDs 430911844450, 813393435573) | G62: 2 | H62: - | I62: 9555076709 | J62: Kanpur | K62: Kanpur | L62: Visit | M62: 19/12/24 12:50pm | N62: 19/12/24 4:50pm | O62: 202
A63: 5 | B63: 59 | C63: Aditya / Ranjana | D63: 20 / 18 | E63: Friend | F63: Indian (ID 870173978032) | G63: 2 | H63: Awas Vikas-86 | I63: VERIFY 8115705855 (first digit 8/0 unclear) | J63: Kanpur | K63: Kanpur | L63: Visit | M63: 21/12/24 12:15pm
A64: 5 | B64: 60 | C64: Pawan / Susma | D64: 22 / 20 | E64: Friend | F64: Indian (IDs 803640462463, 834702701620) | G64: 2 | H64: Hemant Vihar Barra 2 Kanpur | I64: 7368795618 | J64: Kanpur | K64: Kanpur | L64: Visit | M64: 22/12/24 12:15pm | N64: 22/12/24 3:15pm | O64: 201
A65: 6 | B65: 61 | C65: Puja Soni / Ankit Kumar | D65: 21 / 20 | E65: Friend | F65: Indian (IDs 353041501274, 26150413921) | G65: 2 | H65: Parsauli, Kathangar, Kanpur UP | I65: VERIFY 6308668090 | J65: Kanpur | K65: Kanpur | L65: Visit | M65: 22/12/24 1:13pm | N65: 22/12/24 3:40pm | O65: 203
A66: 6 | B66: 62 | C66: Deepu Sonkar / Payal Yadav | D66: 21 / 22 | E66: Friend | F66: India (IDs 233818637967, 820193893644) | G66: 2 | H66: Barra-2, Kanpur | I66: 6394010145 | J66: Kanpur | K66: Kanpur | L66: Visit | M66: 22/12/24 1:02pm | N66: 22/12/24 6:36pm | O66: 204
A67: 6 | B67: 63 | C67: Shivam Kumar / Sneha Pal | D67: 21 / 20 | E67: Friend | F67: Indian (IDs 810040755824, 610963233180) | G67: 2 | H67: Chami Buzurg, Hamirpur UP | I67: 6392813154 | J67: Kanpur | K67: Kanpur | L67: Visit | M67: 23/12/24 3:52pm | N67: 23/12/24 6:22pm | O67: 201
A68: 6 | B68: 64 | C68: Shiva Singh Yadav / Sheelam | D68: 25 | E68: Friend | F68: Indian (ID 801463839103) | G68: 2 | H68: Meharban Singh Ka Purwa | J68: Kanpur | K68: Kanpur | L68: Visit | M68: 23/12/24 7:35pm | N68: 24/12/24 8:00am | O68: 206
A69: 6 | B69: 65 | C69: Sandeep Gupta / Saloni Rathod | D69: 20 / 21 | E69: Friend | F69: Indian (IDs 858598889385, 438672829438) | G69: 2 | H69: 358 Rana Pratap Nagar, KP University | I69: 8957011856 | J69: Kanpur | K69: Kanpur | L69: Visit | M69: 24/12/24 11:35am | N69: 24/12/24 4:05pm | O69: 201
A70: 6 | B70: 66 | C70: Shivam Kumar / Sneha Pal | D70: 21 / 20 | E70: Friend | F70: Indian (IDs 810040755824, 610963233180) | G70: 2 | H70: Chami Buzurg, Hamirpur UP | I70: 6392813154 | J70: Kanpur | K70: Kanpur | L70: Visit | M70: 25/12/24 6:25pm | N70: 25/12/24 8:40pm | O70: 205
A71: 6 | B71: 67 | C71: Santosh Diwakar / Jyoti | D71: 24 / 24 | E71: Friend | F71: Indian (IDs 442301316113, 476830470187) | G71: 2 | H71: Juhi Colony Kanpur | I71: 8858377320 | J71: Kanpur | K71: Kanpur | L71: Visit | M71: 25/12/24 8:10pm | N71: 25/12/24 9:05pm | O71: 203
A72: 6 | B72: 68 | C72: Himanshu / Nikki | D72: 18 / 20 | E72: Friend | F72: India (ID 691078236787) | G72: 2 | H72: Ram Singh Purwa | I72: 7054004283 | J72: Kanpur | K72: Kanpur | L72: Visit | M72: 26/12/24 9:30am | N72: 26/12/24 4:26pm | O72: 205
A73: 6 | B73: 69 | C73: Gulafsha Bano / Mithun | D73: 20 / 19 | E73: Friend | F73: India (IDs 950714446898, 843981561232) | G73: 2 | H73: 131/26 Begum Purwa TP Nagar Kanpur / Binaur Sachendi Bhagwantpur Kanpur | I73: 6387035658 | J73: Kanpur | K73: Kanpur | L73: Visit | M73: 26/12/24 10:40am | N73: 26/12/24 3:06pm | O73: 204
A74: 6 | B74: 70 | C74: Shweta Pathak / Aman Sharma | D74: 19 / 17 | E74: Friend | F74: India (IDs 652812493620, 510544381798) | G74: 2 | H74: 267/2 Rail Bazar, Kanpur Cantt | I74: 9451930495 | J74: Kanpur | K74: Kanpur | L74: Visit | M74: 26/12/24 12:12pm | N74: 26/12/24 2:32pm | O74: 201
A75: 6 | B75: 71 | C75: Naitik Sharma / Arti Prajapati | D75: 23 / 20 | E75: Friend | F75: Indian (IDs 426777347831, 450367271649) | G75: 2 | H75: 175/2 Sanjay Gandhi Nagar | I75: VERIFY 8429360708 (8th digit 7/9 unclear) | J75: Kanpur | K75: Kanpur | L75: Visit | M75: 26/12/24 | N75: 26/12/24 6:44pm | O75: 203
A76: 6 | B76: 72 | C76: Shitanshu / Akhya Gupta | D76: 22 / 27 | E76: Family | F76: Indian (IDs 978605928803, 515562096343) | G76: 2 | H76: Dari Kheda / Kanpur | I76: 7317651956 | J76: Kanpur | K76: Kanpur | L76: Visit | M76: 27/12/24 12:05pm | N76: 27/12/24 2:48pm | O76: 205
A77: 7 | B77: 73 | C77: Ram Prakash / Puja Singh | D77: - / 28 | E77: Friend | F77: Indian | G77: 2 | H77: Dada Nagar Kanpur | I77: 9984182961 | J77: Kanpur | K77: Kanpur | L77: Visit | M77: 27/12/24 3:58pm | N77: 27/12/24 6:54pm | O77: 205
A78: 7 | B78: 74 | C78: Aman Verma | D78: 22 | E78: Friend | F78: Indian | G78: 2 | H78: - | I78: 6394658814 | J78: Kanpur | K78: Kanpur | L78: Visit | M78: 28/12/24 3:06pm | N78: 28/12/24 | O78: 205
A79: 7 | B79: 75 | C79: VERIFY (names unclear) | D79: 30 / 25 | E79: Family | F79: Indian (ID 6658050058421 struck) | G79: 2 | H79: Barra-2 | J79: Kanpur | K79: Kanpur | L79: Visit | M79: 29/12/24 | N79: 29/12/24 | O79: 203
A80: 7 | B80: 76 | C80: Mithun / Gulafsha | D80: 20 / 20 | E80: Friend | F80: Indian (IDs 950714446898, 843981561227) | G80: 2 | H80: Begum Purwa Kanpur / Sachendi Kanpur | I80: VERIFY 7807958257 / 7398067230 | J80: Kanpur | K80: Kanpur | L80: Visit | M80: 29/12/24 | N80: 29/12/24 | O80: 205 / 204
A81: 7 | B81: 77 | C81: Anand / Tanu Kumari (Hindi) | D81: 21 / 22 | E81: Friend | F81: Indian (ID 681547816485) | G81: 2 | H81: Kaindha, Patara, Kanpur Nagar | I81: 7897617417 | J81: Kanpur | K81: Kanpur | L81: Visit | M81: 30/12/24 11:02am | N81: 30/12/24 4:38pm | O81: 206
A82: 7 | B82: 78 | C82: Gaurav Singh / Neha Singh | D82: 25 / 24 | E82: Friend | F82: India (ID 962655474362) | G82: 2 | H82: K.R Palace Kanpur | I82: 8052481945 | J82: Kanpur | K82: Kanpur | L82: Visit | M82: 30/12/24 1:40pm | N82: 30/12/24 2:28pm | O82: 204
A83: 7 | B83: 79 | C83: Shailendra Singh / Abhilasha | D83: 21 / 20 | E83: Family | F83: India (IDs 692621043032, 750548360705) | G83: 2 | H83: Naubasta / Naubasta | I83: VERIFY 7905800319 / 7275261481 | J83: Kanpur | K83: Kanpur | L83: Visit | M83: 31/12/24 | O83: VERIFY 204
A84: 7 | B84: 80 | C84: Ashish Pal / Sonam Pal | D84: 20 / 20 | E84: Family | F84: India (IDs 641173220827, 510927029904) | G84: 2 | H84: Karrahi / Akbarpur | I84: VERIFY 7318168897 | J84: Kanpur | K84: Kanpur | L84: Visit | M84: 31/12/24 12:00pm | O84: 203
A85: 7 | B85: 81 | C85: Ram Prakash / Puja Singh | D85: - / 28 | E85: Friend | F85: India | G85: 2 | H85: Dada Nagar | I85: 9984182961 | J85: Kanpur | K85: Kanpur | L85: Visit | M85: 31/12/24 12:15pm
A86: 7 | B86: 82 | C86: Nitin Dixit / Inshita Mishra | D86: 26 / 20 | E86: Friend | F86: India (IDs 752197909772, 210402421340) | G86: 2 | H86: Dhankutti, Kanpur | I86: 6391291918 | J86: Kanpur | K86: Kanpur | L86: Visit | M86: 1/1/25 12:49pm | N86: 1/1/25 3:23pm | O86: 202
A87: 7 | B87: 83 | C87: Alok Tiwari / Aarti Savita | D87: 21 / 24 | E87: Friend | F87: India (IDs 869854011974, 245808476904) | G87: 2 | H87: Dabauli West / Udyog Nagar Kanpur | I87: 7080956577 | J87: Kanpur | K87: Kanpur | L87: Visit | M87: 1/1/25 12:56pm | N87: 1/1/25 4:46pm | O87: 203
A88: 7 | B88: 84 | C88: Anurag Shukla / Jyoti Verma | D88: 21 / 22 | E88: Friend | F88: India (IDs 210402421340, 354097839013, 692502212679) | G88: 2 | H88: C-684 World Bank Barra, Kanpur | I88: 9335681236 | J88: Kanpur | K88: Kanpur | L88: Visit | M88: 1/1/25 1:39pm | N88: 1/1/25 6:26pm | O88: 204
A89: 8 | B89: 85 | C89: Aditya Sahu / Ritu Raikwar | D89: 30 / 24 | E89: Friend | F89: Indian (IDs 617989404989, 39746642866) | G89: 2 | H89: K-49 World Bank Barra Colony, Kanpur | I89: 9044133973 | J89: Kanpur | K89: Kanpur | L89: Visit | M89: 1/1/25 1:57pm | N89: 1/1/25 4:48pm | O89: 202
A90: 8 | B90: 86 | C90: Ayush Yadav / Aastha | D90: 19 / 20 | E90: Friend | F90: Indian (IDs 420143136425, 663214513519) | G90: 2 | H90: Salempur, Panara, Fatehpur, Kanpur | J90: Kanpur | K90: Kanpur | L90: Visit | M90: 1/1/25 2:08pm | N90: 1/1/25 4:20pm | O90: 206
A91: 8 | B91: 87 | C91: Abhay Kumar / Rashmi Devi | D91: 19 / 25 | E91: Friend | F91: Indian (IDs 726166027255, 896782030169) | G91: 2 | H91: Bhagwantpur, Sachendi, Binaur, Kanpur | I91: 7678810279 / 7268014982 | J91: Kanpur | K91: Kanpur | L91: Visit | M91: 1/1/25 4:17pm | N91: 2/1/25 7:18am | O91: 206
A92: 8 | B92: 88 | C92: Kapil Bhatt | D92: 19 | E92: Friends | F92: India (ID 78269772467) | G92: 6 | H92: Barra 8, E Block, Kanpur | I92: 6387221857 | J92: Kanpur | K92: Kanpur | L92: Visit | M92: 2/1/25 12:25pm | N92: 2/1/25 | O92: 204
A93: 8 | B93: 89 | C93: Pawan Gupta / Priya Gupta | D93: 42 / 36 | E93: Wife | F93: Indian (IDs 959824095832, 341806674830) | G93: 2 | H93: Ambedkar Nagar, Auraiya | I93: 8218905563 / 9889066081 | J93: Auraiya | K93: Auraiya | L93: Relation | M93: 2/1/25 11:42am | N93: 2/1/25 | O93: 202
A94: 8 | B94: 90 | C94: Amit Pal / Shakshi | D94: 25 / 23 | E94: Friend | F94: Indian (IDs 881719681296, 426183674046) | G94: 2 | H94: Jarauli Phase-2, Bihari Purwa, Barra Kanpur | I94: 7380621774 | J94: Kanpur | K94: Kanpur | L94: Visit | M94: 2/1/25 12:08pm | N94: 3/1/25 | O94: 202
A95: 8 | B95: 91 | C95: Naitik Sharma / Arti Prajapati | D95: 23 / 21 | E95: Friend | F95: Indian (IDs 426777347831, 450367271649) | G95: 2 | H95: 175/2 Sanjay Nagar, Gandhi Nagar | I95: 8429360708 | J95: Kanpur | K95: Kanpur | L95: Visit | M95: 3/1/25 | N95: 3/1/25 | O95: 201
A96: 8 | B96: 92 | C96: Aditya Sahu / Ritu | D96: 30 / 24 | E96: Friend | F96: India (IDs 617989404989, 39746642866) | G96: 2 | H96: K-49 World Bank Barra Colony, Kanpur | I96: 9044133973 | J96: Kanpur | K96: Kanpur | L96: Visit | M96: 3/1/25 1:28pm | N96: 3/1/25 | O96: 202
A97: 8 | B97: 93 | C97: Arpit Mishra / Sonali Mishra | D97: 19 / 19 | E97: Friend | F97: Indian | G97: 2 | H97: 6A-529, Kanpur | I97: 9236916732 | J97: Kanpur | K97: Kanpur | L97: Visit | M97: 3/1/25 5:18pm | N97: 3/1/25 | O97: 201
A98: 8 | B98: 94 | C98: Aditya Sahu | D98: 30 | E98: Friend | F98: India (ID 617989404989) | G98: 3 | H98: K-49 World Bank Barra Colony, Kanpur | I98: 9044133973 | J98: Kanpur | K98: Kanpur | L98: Visit | M98: 4/1/25 12:17am | N98: 4/1/25 | O98: 201
A99: 8 | B99: 95 | C99: Zishan Ahmed / Rabiya Khan | D99: 43 / 42 | E99: Friend | F99: Indian (IDs 438859390192, 794868564596) | G99: 2 | H99: 117/84 P Block, Kakadeo, Naveen Nagar | I99: 9696911758 | J99: Kanpur | K99: Kanpur | L99: Visit | M99: 4/1/25 6:18am | N99: 4/1/25 | O99: 204
A100: 8 | B100: 96 | C100: Himanshu / Nikki | D100: 18 / 20 | E100: Friend | F100: Indian (ID 691078256787) | G100: 2 | H100: Ram Singh Purwa | I100: 7054004283 | J100: Kanpur | K100: Kanpur | L100: Visit | M100: 4/1/25 9:08am | N100: 4/1/25 6:48pm | O100: 203
A101: 9 | B101: 97 | C101: Pranjal Gautam / Sanya Gautam | D101: 23 / 25 | E101: Friend | F101: Indian (IDs 693435170476, 623549992258) | G101: 2 | H101: Kaindha, Panki, Kanpur Nagar | I101: 8112634638 | J101: Kanpur | K101: Kanpur | L101: Visit | M101: 5/1/25 10:25am | N101: 5/1/25 2:44pm | O101: 203
...

Sheet Hisaab Bookings
A1: R.R. Garden — Room Rate Ledger (raw bookings, from June–July 2026 diary pages)
A2: Each row = one room booking on that date. Source: handwritten diary, last 2 pages of scan.
A4: Date | B4: Amount
A5: 2026-05-31 | B5: 800
A6: 2026-06-01 | B6: 800
A7: 2026-06-03 | B7: 600
A8: 2026-06-04 | B8: 600
A9: 2026-06-05 | B9: 500
A10: 2026-06-05 | B10: 500
A11: 2026-06-07 | B11: 650
A12: 2026-06-07 | B12: 630
A13: 2026-06-07 | B13: 600
A14: 2026-06-07 | B14: 600
A15: 2026-06-10 | B15: 600
A16: 2026-06-13 | B16: 530
... A47: 2026-07-04 | B47: 520

Sheet Monthly Rate Trend
A1: R.R. Garden — Monthly Room Rate Trend
A2: Auto-calculated from "Hisaab Bookings" sheet using AVERAGEIFS/COUNTIFS/MIN/MAXIFS. Add new months to Hisaab Bookings and this updates automatically.
A4: Month | B4: Bookings | C4: Avg Rate (Rs) | D4: Min Rate (Rs) | E4: Max Rate (Rs) | F4: Total Revenue (Rs)
A5: May 2026 | B5: =COUNTIFS('Hisaab Bookings'!$A$5:$A$47,">="&DATE(2026,5,1),'Hisaab Bookings'!$A$5:$A$47,"<="&DATE(2026,5,31)) | C5: =IFERROR(AVERAGEIFS('Hisaab Bookings'!$B$5:$B$47,'Hisaab Bookings'!$A$5:$A$47,">="&DATE(2026,5,1),'Hisaab Bookings'!$A$5:$A$47,"<="&DATE(2026,5,31)),0) | D5: =IFERROR(minifs('Hisaab Bookings'!$B$5:$B$47,'Hisaab Bookings'!$A$5:$A$47,">="&DATE(2026,5,1),'Hisaab Bookings'!$A$5:$A$47,"<="&DATE(2026,5,31)),0) | E5: =IFERROR(maxifs('Hisaab Bookings'!$B$5:$B$47,'Hisaab Bookings'!$A$5:$A$47,">="&DATE(2026,5,1),'Hisaab Bookings'!$A$5:$A$47,"<="&DATE(2026,5,31)),0) | F5: =IFERROR(SUMIFS('Hisaab Bookings'!$B$5:$B$47,'Hisaab Bookings'!$A$5:$A$47,">="&DATE(2026,5,1),'Hisaab Bookings'!$A$5:$A$47,"<="&DATE(2026,5,31)),0)
A6: June 2026 | B6: =COUNTIFS('Hisaab Bookings'!$A$5:$A$47,">="&DATE(2026,6,1),'Hisaab Bookings'!$A$5:$A$47,"<="&DATE(2026,6,30)) | C6: =IFERROR(AVERAGEIFS('Hisaab Bookings'!$B$5:$B$47,'Hisaab Bookings'!$A$5:$A$47,">="&DATE(2026,6,1),'Hisaab Bookings'!$A$5:$A$47,"<="&DATE(2026,6,30)),0) | D6: =IFERROR(minifs('Hisaab Bookings'!$B$5:$B$47,'Hisaab Bookings'!$A$5:$A$47,">="&DATE(2026,6,1),'Hisaab Bookings'!$A$5:$A$47,"<="&DATE(2026,6,30)),0) | E6: =IFERROR(maxifs('Hisaab Bookings'!$B$5:$B$47,'Hisaab Bookings'!$A$5:$A$47,">="&DATE(2026,6,1),'Hisaab Bookings'!$A$5:$A$47,"<="&DATE(2026,6,30)),0) | F6: =IFERROR(SUMIFS('Hisaab Bookings'!$B$5:$B$47,'Hisaab Bookings'!$A$5:$A$47,">="&DATE(2026,6,1),'Hisaab Bookings'!$A$5:$A$47,"<="&DATE(2026,6,30)),0)
A7: July 2026 | B7: =COUNTIFS('Hisaab Bookings'!$A$5:$A$47,">="&DATE(2026,7,1),'Hisaab Bookings'!$A$5:$A$47,"<="&DATE(2026,7,31)) | C7: =IFERROR(AVERAGEIFS('Hisaab Bookings'!$B$5:$B$47,'Hisaab Bookings'!$A$5:$A$47,">="&DATE(2026,7,1),'Hisaab Bookings'!$A$5:$A$47,"<="&DATE(2026,7,31)),0) | D7: =IFERROR(minifs('Hisaab Bookings'!$B$5:$B$47,'Hisaab Bookings'!$A$5:$A$47,">="&DATE(2026,7,1),'Hisaab Bookings'!$A$5:$A$47,"<="&DATE(2026,7,31)),0) | E7: =IFERROR(maxifs('Hisaab Bookings'!$B$5:$B$47,'Hisaab Bookings'!$A$5:$A$47,">="&DATE(2026,7,1),'Hisaab Bookings'!$A$5:$A$47,"<="&DATE(2026,7,31)),0) | F7: =IFERROR(SUMIFS('Hisaab Bookings'!$B$5:$B$47,'Hisaab Bookings'!$A$5:$A$47,">="&DATE(2026,7,1),'Hisaab Bookings'!$A$5:$A$47,"<="&DATE(2026,7,31)),0)
A8: All-time (loaded data) | B8: =COUNT('Hisaab Bookings'!$B$5:$B$47) | C8: =AVERAGE('Hisaab Bookings'!$B$5:$B$47) | D8: =MIN('Hisaab Bookings'!$B$5:$B$47) | E8: =MAX('Hisaab Bookings'!$B$5:$B$47) | F8: =SUM('Hisaab Bookings'!$B$5:$B$47)

Sheet Settlement Notes
A1: R.R. Garden — Income Split / Settlement Notes (from diary)
A2: These are running settlement notes found under the June/July totals — meaning not 100% certain, please confirm. Likely a split of room income between people (Uncle, Ansh, Malwa) plus online vs cash tracking and balance due.
A4: June (first half, 31 May – 14 Jun)
A5: Total | B5: 10930
A6: Uncle | B6: 8100
A7: Ansh | B7: 900
A8: Malwa | B8: 1000
A9: Online | B9: 700
A10: Baki hai (balance due) | B10: 200
A12: June (second half, 15–30 Jun)
A13: Total | B13: 11830
A14: Uncle+Ansh | B14: 1050
A15: Malwa | B15: 2000
A16: VERIFY (unclear label) | B16: 700
A17: VERIFY (unclear label) | B17: 170
A18: Dena hai (to be paid) | B18: 2010
A19: Baki (balance due) | B19: 200
A20: Total settlement | B20: 2810

Sheet Expenses
A1: R.R. Garden — Expenses Tracker
A2: Log ongoing expenses here (repairs, supplies, staff, electricity, etc.) to net against booking revenue.
A4: Date | B4: Category | C4: Description | D4: Amount (Rs) | E4: Paid By | F4: Notes
C41: Total | D41: =SUM(D5:D40)

Sheet Monthly Bookings & Ansh
A1: Monthly Bookings & Ansh Commission
A2: Booking count from Guest Register ArrivalDateTime. Commission = Rs 50/booking; manager remits within 15 days minus commission.
A4: Month | B4: Bookings | C4: Commission (Rs 50/booking)
A5: 11/2024 | B5: =COUNTIF('Guest Register'!$M$5:$M$10000,"*/11/24 *")+COUNTIF('Guest Register'!$M$5:$M$10000,"*/11/24") | C5: =B5*50
A6: 12/2024 | B6: =COUNTIF('Guest Register'!$M$5:$M$10000,"*/12/24 *")+COUNTIF('Guest Register'!$M$5:$M$10000,"*/12/24") | C6: =B6*50
A7: 01/2025 | B7: =COUNTIF('Guest Register'!$M$5:$M$10000,"*/1/25 *")+COUNTIF('Guest Register'!$M$5:$M$10000,"*/1/25")+COUNTIF('Guest Register'!$M$5:$M$10000,"*/01/25 *")+COUNTIF('Guest Register'!$M$5:$M$10000,"*/01/25") | C7: =B7*50
A8: 02/2025 | B8: =COUNTIF('Guest Register'!$M$5:$M$10000,"*/2/25 *")+COUNTIF('Guest Register'!$M$5:$M$10000,"*/2/25")+COUNTIF('Guest Register'!$M$5:$M$10000,"*/02/25 *")+COUNTIF('Guest Register'!$M$5:$M$10000,"*/02/25") | C8: =B8*50
A9: 03/2025 | B9: =COUNTIF('Guest Register'!$M$5:$M$10000,"*/3/25 *")+COUNTIF('Guest Register'!$M$5:$M$10000,"*/3/25")+COUNTIF('Guest Register'!$M$5:$M$10000,"*/03/25 *")+COUNTIF('Guest Register'!$M$5:$M$10000,"*/03/25") | C9: =B9*50
A10: 04/2025 | B10: =COUNTIF('Guest Register'!$M$5:$M$10000,"*/4/25 *")+COUNTIF('Guest Register'!$M$5:$M$10000,"*/4/25")+COUNTIF('Guest Register'!$M$5:$M$10000,"*/04/25 *")+COUNTIF('Guest Register'!$M$5:$M$10000,"*/04/25") | C10: =B10*50
A11: 05/2025 | B11: =COUNTIF('Guest Register'!$M$5:$M$10000,"*/5/25 *")+COUNTIF('Guest Register'!$M$5:$M$10000,"*/5/25")+COUNTIF('Guest Register'!$M$5:$M$10000,"*/05/25 *")+COUNTIF('Guest Register'!$M$5:$M$10000,"*/05/25") | C11: =B11*50
A12: 06/2025 | B12: =COUNTIF('Guest Register'!$M$5:$M$10000,"*/6/25 *")+COUNTIF('Guest Register'!$M$5:$M$10000,"*/6/25")+COUNTIF('Guest Register'!$M$5:$M$10000,"*/06/25 *")+COUNTIF('Guest Register'!$M$5:$M$10000,"*/06/25") | C12: =B12*50
A13: 07/2025 | B13: =COUNTIF('Guest Register'!$M$5:$M$10000,"*/7/25 *")+COUNTIF('Guest Register'!$M$5:$M$10000,"*/7/25")+COUNTIF('Guest Register'!$M$5:$M$10000,"*/07/25 *")+COUNTIF('Guest Register'!$M$5:$M$10000,"*/07/25") | C13: =B13*50
A14: 08/2025 | B14: =COUNTIF('Guest Register'!$M$5:$M$10000,"*/8/25 *")+COUNTIF('Guest Register'!$M$5:$M$10000,"*/8/25")+COUNTIF('Guest Register'!$M$5:$M$10000,"*/08/25 *")+COUNTIF('Guest Register'!$M$5:$M$10000,"*/08/25") | C14: =B14*50
A15: 09/2025 | B15: =COUNTIF('Guest Register'!$M$5:$M$10000,"*/9/25 *")+COUNTIF('Guest Register'!$M$5:$M$10000,"*/9/25")+COUNTIF('Guest Register'!$M$5:$M$10000,"*/09/25 *")+COUNTIF('Guest Register'!$M$5:$M$10000,"*/09/25") | C15: =B15*50
A16: 10/2025 | B16: =COUNTIF('Guest Register'!$M$5:$M$10000,"*/10/25 *")+COUNTIF('Guest Register'!$M$5:$M$10000,"*/10/25") | C16: =B16*50
A17: 11/2025 | B17: =COUNTIF('Guest Register'!$M$5:$M$10000,"*/11/25 *")+COUNTIF('Guest Register'!$M$5:$M$10000,"*/11/25") | C17: =B17*50
A18: 12/2025 | B18: =COUNTIF('Guest Register'!$M$5:$M$10000,"*/12/25 *")+COUNTIF('Guest Register'!$M$5:$M$10000,"*/12/25") | C18: =B18*50
A19: 01/2026 | B19: =COUNTIF('Guest Register'!$M$5:$M$10000,"*/1/26 *")+COUNTIF('Guest Register'!$M$5:$M$10000,"*/1/26")+COUNTIF('Guest Register'!$M$5:$M$10000,"*/01/26 *")+COUNTIF('Guest Register'!$M$5:$M$10000,"*/01/26") | C19: =B19*50
A20: 02/2026 | B20: =COUNTIF('Guest Register'!$M$5:$M$10000,"*/2/26 *")+COUNTIF('Guest Register'!$M$5:$M$10000,"*/2/26")+COUNTIF('Guest Register'!$M$5:$M$10000,"*/02/26 *")+COUNTIF('Guest Register'!$M$5:$M$10000,"*/02/26") | C20: =B20*50
A21: 03/2026 | B21: =COUNTIF('Guest Register'!$M$5:$M$10000,"*/3/26 *")+COUNTIF('Guest Register'!$M$5:$M$10000,"*/3/26")+COUNTIF('Guest Register'!$M$5:$M$10000,"*/03/26 *")+COUNTIF('Guest Register'!$M$5:$M$10000,"*/03/26") | C21: =B21*50
A22: 04/2026 | B22: =COUNTIF('Guest Register'!$M$5:$M$10000,"*/4/26 *")+COUNTIF('Guest Register'!$M$5:$M$10000,"*/4/26")+COUNTIF('Guest Register'!$M$5:$M$10000,"*/04/26 *")+COUNTIF('Guest Register'!$M$5:$M$10000,"*/04/26") | C22: =B22*50
A23: 05/2026 | B23: =COUNTIF('Guest Register'!$M$5:$M$10000,"*/5/26 *")+COUNTIF('Guest Register'!$M$5:$M$10000,"*/5/26")+COUNTIF('Guest Register'!$M$5:$M$10000,"*/05/26 *")+COUNTIF('Guest Register'!$M$5:$M$10000,"*/05/26") | C23: =B23*50
A24: 06/2026 | B24: =COUNTIF('Guest Register'!$M$5:$M$10000,"*/6/26 *")+COUNTIF('Guest Register'!$M$5:$M$10000,"*/6/26")+COUNTIF('Guest Register'!$M$5:$M$10000,"*/06/26 *")+COUNTIF('Guest Register'!$M$5:$M$10000,"*/06/26") | C24: =B24*50
A25: 07/2026 | B25: =COUNTIF('Guest Register'!$M$5:$M$10000,"*/7/26 *")+COUNTIF('Guest Register'!$M$5:$M$10000,"*/7/26")+COUNTIF('Guest Register'!$M$5:$M$10000,"*/07/26 *")+COUNTIF('Guest Register'!$M$5:$M$10000,"*/07/26") | C25: =B25*50
A26: TOTAL | B26: =SUM(B5:B25) | C26: =SUM(C5:C25)
